geometry/__init__.py
geometry/line.py
geometry/point.py
geometry/triangle.py
my_geometry_lib-0.11.dist-info/METADATA
my_geometry_lib-0.11.dist-info/WHEEL
my_geometry_lib-0.11.dist-info/top_level.txt
my_geometry_lib-0.11.dist-info/RECORD
