Metadata-Version: 2.1
Name: my-geometry-lib
Version: 0.11
Summary: Test library
Home-page: https://github.com/Xorsiphus
Author: Evgeniy
License: UNKNOWN
Platform: UNKNOWN
